{
  "objectInfo" : {
    "id" : "k8CvbWUmvm5dXlEeLeOqQz",
    "name" : "ICRT-4818-255",
    "type" : "PROCESS",
    "metadata" : {
      "modelVersion" : {
        "major" : 1,
        "minor" : 0
      },
      "repoInfo" : {
        "repoHandle" : "soq3xgjATO9pH8s-gt-20277-2022-09-06T13:08:12.303Z::pd.xml"
      },
      "contextAttributes" : null,
      "additionalInfo" : {
        "description" : null,
        "contentType" : "Binary",
        "documentState" : "VALID"
      }
    }
  },
  "dataFileExtension" : "xml",
  "objectRefs" : [ ]
}