{
  "objectInfo" : {
    "id" : "9mBbdWREWRhiSJevGzHz2b",
    "name" : "ICRT-4818-472",
    "type" : "PROCESS",
    "metadata" : {
      "modelVersion" : {
        "major" : 1,
        "minor" : 0
      },
      "repoInfo" : {
        "repoHandle" : "QzqbdpIO3M4WwOC-gt-24127-2022-10-28T17:02:42.681Z::pd.xml"
      },
      "contextAttributes" : null,
      "additionalInfo" : {
        "description" : null,
        "contentType" : "Binary",
        "documentState" : "VALID"
      }
    }
  },
  "dataFileExtension" : "xml",
  "objectRefs" : [ ]
}