{
  "objectInfo" : {
    "id" : "3sHwpxdj44diEmv0MIAIEz",
    "name" : "ImportGuideWithPublishGit",
    "type" : "GUIDE",
    "metadata" : {
      "modelVersion" : {
        "major" : 1,
        "minor" : 0
      },
      "repoInfo" : {
        "repoHandle" : "AUigdpIO3M4WwOC-gt-924-2022-06-07T12:34:34.421Z::gt.xml"
      },
      "contextAttributes" : null,
      "additionalInfo" : {
        "description" : "",
        "contentType" : "application/json; charset=utf-8",
        "documentState" : "VALID"
      }
    }
  },
  "dataFileExtension" : "xml",
  "objectRefs" : [ ]
}