{
  "objectInfo" : {
    "id" : "1DLi6nVTVm2kOLfakdeE4M",
    "name" : "ImportProcessWithPublishGit",
    "type" : "PROCESS",
    "metadata" : {
      "modelVersion" : {
        "major" : 1,
        "minor" : 0
      },
      "repoInfo" : {
        "repoHandle" : "7ZLPJljxcghuImX-gt-110105-2021-09-21T10:28:27.937Z::pd.xml"
      },
      "contextAttributes" : null,
      "additionalInfo" : {
        "description" : "",
        "contentType" : "application/json; charset=utf-8",
        "documentState" : "VALID"
      }
    }
  },
  "dataFileExtension" : "xml",
  "objectRefs" : [ ]
}