{
  "objectInfo" : {
    "id" : "iD2qciJqa27b9I0Cvgi8QR",
    "name" : "ImportSvcConnWithPublishGit",
    "type" : "AI_SERVICE_CONNECTOR",
    "metadata" : {
      "modelVersion" : {
        "major" : 1,
        "minor" : 0
      },
      "repoInfo" : {
        "repoHandle" : "Brx8AyNnQMMnGbc-gt-56332-2021-11-30T15:28:42.439Z::svc.xml"
      },
      "contextAttributes" : null,
      "additionalInfo" : {
        "description" : "this is Service Connector",
        "contentType" : "application/json; charset=utf-8",
        "documentState" : "VALID"
      }
    }
  },
  "dataFileExtension" : "xml",
  "objectRefs" : [ ]
}