{
  "objectInfo" : {
    "id" : "jkzqsvLYngCfPIR0lDmAGs",
    "name" : "ImportPOAndVerifyGit",
    "type" : "PROCESS_OBJECT",
    "metadata" : {
      "modelVersion" : {
        "major" : 1,
        "minor" : 0
      },
      "repoInfo" : {
        "repoHandle" : "i6X4ZnchKGXShOe-gt-101964-2022-04-03T21:06:05.138Z::po.xml"
      },
      "contextAttributes" : null,
      "additionalInfo" : {
        "description" : "This is used by automation",
        "contentType" : "application/json; charset=utf-8",
        "documentState" : "VALID"
      }
    }
  },
  "dataFileExtension" : "xml",
  "objectRefs" : [ ]
}