{
  "objectInfo" : {
    "id" : "fog8s21oSUUfBdf1zvJj4Q",
    "name" : "ImportProcessWithPublishGit",
    "type" : "PROCESS",
    "metadata" : {
      "modelVersion" : {
        "major" : 1,
        "minor" : 0
      },
      "repoInfo" : {
        "repoHandle" : "8LPJljxcghuImXy-gt-8167-2022-06-10T04:51:37.967Z::pd.xml"
      },
      "contextAttributes" : null,
      "additionalInfo" : {
        "description" : "",
        "contentType" : "application/json; charset=utf-8",
        "documentState" : "VALID"
      }
    }
  },
  "dataFileExtension" : "xml",
  "objectRefs" : [ ]
}