{
  "objectInfo" : {
    "id" : "9RSGTwhLv28fimTwmqaBe6",
    "name" : "zImportConnWithPublishGit",
    "type" : "AI_CONNECTION",
    "metadata" : {
      "modelVersion" : {
        "major" : 1,
        "minor" : 0
      },
      "repoInfo" : {
        "repoHandle" : "BwDPWNMZQELaabc-gt-16984-2022-10-16T23:13:02.345Z::conn.xml"
      },
      "contextAttributes" : null,
      "additionalInfo" : {
        "description" : "a",
        "contentType" : "application/json; charset=utf-8",
        "documentState" : "VALID"
      }
    }
  },
  "dataFileExtension" : "xml",
  "objectRefs" : [ {
    "id" : "iep8SOTuX81jubMbx3sz2c",
    "name" : "ImportSvcConnWithPublishGit",
    "type" : "AI_SERVICE_CONNECTOR",
    "metadata" : {
      "modelVersion" : {
        "major" : 1,
        "minor" : 0
      },
      "repoInfo" : {
        "repoHandle" : "DnFShFdw8jIw8jI-gt-16950-2022-10-16T23:13:01.547Z::svc.xml"
      },
      "contextAttributes" : null,
      "additionalInfo" : {
        "description" : "this is Service Connector",
        "contentType" : "application/json; charset=utf-8",
        "documentState" : "VALID"
      }
    },
    "path" : "/Explore/Git"
  } ]
}