{
  "objectInfo" : {
    "id" : "2oLAFmkF0HScH9iG3UWteN",
    "name" : "zImportConnWithPublishGit",
    "type" : "AI_CONNECTION",
    "metadata" : {
      "modelVersion" : {
        "major" : 1,
        "minor" : 0
      },
      "repoInfo" : {
        "repoHandle" : "u9oPiciT6sFsdsF-gt-1615271-2022-06-02T12:31:18.331Z::conn.xml"
      },
      "contextAttributes" : null,
      "additionalInfo" : {
        "description" : "a",
        "contentType" : "application/json; charset=utf-8",
        "documentState" : "VALID"
      }
    }
  },
  "dataFileExtension" : "xml",
  "objectRefs" : [ {
    "id" : "8z05028IqNjlAnpHiikKKh",
    "name" : "ImportSvcConnWithPublishGit",
    "type" : "AI_SERVICE_CONNECTOR",
    "metadata" : {
      "modelVersion" : {
        "major" : 1,
        "minor" : 0
      },
      "repoInfo" : {
        "repoHandle" : "I1iUsRvsGRvDINc-gt-1609987-2022-06-02T12:31:17.564Z::svc.xml"
      },
      "contextAttributes" : null,
      "additionalInfo" : {
        "description" : "this is Service Connector",
        "contentType" : "application/json; charset=utf-8",
        "documentState" : "VALID"
      }
    },
    "path" : "/Explore/Git"
  } ]
}