{
  "objectInfo" : {
    "id" : "l0rkP4ZZhenbn5MRxwhEAD",
    "name" : "zImportConnWithPublishGit",
    "type" : "AI_CONNECTION",
    "metadata" : {
      "modelVersion" : {
        "major" : 1,
        "minor" : 0
      },
      "repoInfo" : {
        "repoHandle" : "T9DoWn2sqeErhNz-gt-45412-2022-02-01T04:50:32.741Z::conn.xml"
      },
      "contextAttributes" : null,
      "additionalInfo" : {
        "description" : "a",
        "contentType" : "application/json; charset=utf-8",
        "documentState" : "VALID"
      }
    }
  },
  "dataFileExtension" : "xml",
  "objectRefs" : [ {
    "id" : "5epGqvMl2E0bK4aFrvua23",
    "name" : "ImportSvcConnWithPublishGit",
    "type" : "AI_SERVICE_CONNECTOR",
    "metadata" : {
      "modelVersion" : {
        "major" : 1,
        "minor" : 0
      },
      "repoInfo" : {
        "repoHandle" : "g7wporzYLnzYLnz-gt-45011-2022-02-01T04:50:32.097Z::svc.xml"
      },
      "contextAttributes" : null,
      "additionalInfo" : {
        "description" : "this is Service Connector",
        "contentType" : "application/json; charset=utf-8",
        "documentState" : "VALID"
      }
    },
    "path" : "/Explore/Git"
  } ]
}