<aetgt:getResponse xmlns:aetgt="http://schemas.active-endpoints.com/appmodules/repository/2010/10/avrepository.xsd"
                   xmlns:types1="http://schemas.active-endpoints.com/appmodules/repository/2010/10/avrepository.xsd">
   <types1:Item>
      <types1:EntryId>5hJdypKwKBqRi92-gt-11047-2021-09-14T08:28:31.917Z::gt.xml</types1:EntryId>
      <types1:Name>ImportGuideWithPublish</types1:Name>
      <types1:MimeType>application/xml+screenflow</types1:MimeType>
      <types1:Description/>
      <types1:AppliesTo/>
      <types1:Tags/>
      <types1:VersionLabel>1.0</types1:VersionLabel>
      <types1:State>CURRENT</types1:State>
      <types1:ProcessGroup/>
      <types1:CreatedBy>vdrelpod1</types1:CreatedBy>
      <types1:CreationDate>2021-09-14T08:28:32Z</types1:CreationDate>
      <types1:ModifiedBy/>
      <types1:PublicationStatus>published</types1:PublicationStatus>
      <types1:PublishedBy>vdrelpod1</types1:PublishedBy>
      <types1:PublicationDate>2021-09-14T08:28:36Z</types1:PublicationDate>
      <types1:PublishedContributionId>project:/sf.ImportGuideWithPublish/ImportGuideWithPublish.xml</types1:PublishedContributionId>
      <types1:AutosaveExists>false</types1:AutosaveExists>
      <types1:Entry>
         <avosScreenflow xmlns="http://schemas.active-endpoints.com/appmodules/screenflow/2010/10/avosScreenflow.xsd"
                         xmlns:list="urn:activevos:spi:list:functions"
                         allowRestart="true"
                         displayName="ImportGuideWithPublish"
                         doneOnEndStep="false"
                         name="ImportGuideWithPublish"
                         runAsUser="$current">
            <description/>
            <appliesTo/>
            <tags/>
            <generator>Informatica Process Designer 11</generator>
            <runOn target="desktop"/>
            <notes/>
            <deployment/>
            <sendFeedback>
               <emailTo/>
            </sendFeedback>
            <flow>
               <startScreen id="jd300kk3">
                  <title>Start</title>
                  <body contentType="text/html"/>
                  <actions>
                     <action alt="null" id="jd300kk3_jd4cwa59" targetScreen="jd4cwa59">
                        <text>Continue</text>
                     </action>
                  </actions>
                  <screenData skipIfRequiredFilled="true"/>
               </startScreen>
               <endScreen id="jd4cwa59">
                  <title>End</title>
                  <body contentType="text/html"/>
                  <redirectTo type="current_object"/>
                  <screenActionLabel>
                     <text/>
                  </screenActionLabel>
               </endScreen>
            </flow>
         </avosScreenflow>
      </types1:Entry>
      <types1:GUID>dTnXXDzmJODjc9Ewod8m0V</types1:GUID>
      <types1:DisplayName>ImportGuideWithPublish</types1:DisplayName>
   </types1:Item>
   <types1:CurrentServerDateTime>2021-09-14T08:47:33.539Z</types1:CurrentServerDateTime>
</aetgt:getResponse>
